<annotation>
	<folder>images</folder>
	<filename>00007557_026.png</filename>
	<path>/Users/yuxuan/Desktop/xraydataset/images/00007557_026.png</path>
	<source>
		<database>nih</database>
	</source>
	<size>
		<width>1024</width>
		<height>1024</height>
		<depth>3</depth>
	</size>
	<segmented>0</segmented>
	<object>
		<name>Atelectasis</name>
		<pose>Unspecified</pose>
		<truncated>0</truncated>
		<difficult>0</difficult>
		<bndbox>
			<xmin>131.796610169492</xmin>
			<ymin>706.476843882415</ymin>
			<xmax>353.08474576271203</xmax>
			<ymax>830.137860831568</ymax>
		</bndbox>
	</object>
</annotation>