<annotation>
	<folder>images</folder>
	<filename>00018102_001.png</filename>
	<path>/Users/yuxuan/Desktop/xraydataset/images/00018102_001.png</path>
	<source>
		<database>nih</database>
	</source>
	<size>
		<width>1024</width>
		<height>1024</height>
		<depth>3</depth>
	</size>
	<segmented>0</segmented>
	<object>
		<name>Effusion</name>
		<pose>Unspecified</pose>
		<truncated>0</truncated>
		<difficult>0</difficult>
		<bndbox>
			<xmin>107.52</xmin>
			<ymin>588.553489583333</ymin>
			<xmax>146.2044444444444</xmax>
			<ymax>642.0290451388886</ymax>
		</bndbox>
	</object>
</annotation>