<annotation>
	<folder>images</folder>
	<filename>00015895_017.png</filename>
	<path>/Users/yuxuan/Desktop/xraydataset/images/00015895_017.png</path>
	<source>
		<database>nih</database>
	</source>
	<size>
		<width>1024</width>
		<height>1024</height>
		<depth>3</depth>
	</size>
	<segmented>0</segmented>
	<object>
		<name>Effusion</name>
		<pose>Unspecified</pose>
		<truncated>0</truncated>
		<difficult>0</difficult>
		<bndbox>
			<xmin>719.508994708995</xmin>
			<ymin>355.420105820106</ymin>
			<xmax>876.630687830688</xmax>
			<ymax>877.714285714286</ymax>
		</bndbox>
	</object>
</annotation>