<annotation>
	<folder>images</folder>
	<filename>00029464_015.png</filename>
	<path>/Users/yuxuan/Desktop/xraydataset/images/00029464_015.png</path>
	<source>
		<database>nih</database>
	</source>
	<size>
		<width>1024</width>
		<height>1024</height>
		<depth>3</depth>
	</size>
	<segmented>0</segmented>
	<object>
		<name>Atelectasis</name>
		<pose>Unspecified</pose>
		<truncated>0</truncated>
		<difficult>0</difficult>
		<bndbox>
			<xmin>198.940451388889</xmin>
			<ymin>352.900746527778</ymin>
			<xmax>814.478229166667</xmax>
			<ymax>676.0296354166669</ymax>
		</bndbox>
	</object>
	<object>
		<name>Effusion</name>
		<pose>Unspecified</pose>
		<truncated>0</truncated>
		<difficult>0</difficult>
		<bndbox>
			<xmin>719.644444444444</xmin>
			<ymin>611.309045138889</ymin>
			<xmax>910.791111111111</xmax>
			<ymax>662.5090451388891</ymax>
		</bndbox>
	</object>
</annotation>