<annotation>
	<folder>images</folder>
	<filename>00027556_007.png</filename>
	<path>/Users/yuxuan/Desktop/xraydataset/images/00027556_007.png</path>
	<source>
		<database>nih</database>
	</source>
	<size>
		<width>1024</width>
		<height>1024</height>
		<depth>3</depth>
	</size>
	<segmented>0</segmented>
	<object>
		<name>Mass</name>
		<pose>Unspecified</pose>
		<truncated>0</truncated>
		<difficult>0</difficult>
		<bndbox>
			<xmin>70.4338624338624</xmin>
			<ymin>196.131216931217</ymin>
			<xmax>240.5587301587304</xmax>
			<ymax>432.355555555556</ymax>
		</bndbox>
	</object>
	<object>
		<name>Atelectasis</name>
		<pose>Unspecified</pose>
		<truncated>0</truncated>
		<difficult>0</difficult>
		<bndbox>
			<xmin>172.292063492064</xmin>
			<ymin>645.824338624339</ymin>
			<xmax>310.992592592593</xmax>
			<ymax>760.685714285715</ymax>
		</bndbox>
	</object>
</annotation>